pyskynet-0.0.3.dist-info/METADATA
pyskynet-0.0.3.dist-info/entry_points.txt
pyskynet-0.0.3.dist-info/RECORD
pyskynet-0.0.3.dist-info/top_level.txt
pyskynet-0.0.3.dist-info/LICENSE
pyskynet-0.0.3.dist-info/WHEEL
pyskynet.libs/libtinfo-6ad58be8.so.5.7
pyskynet.libs/libreadline-5adeae88.so.6.0
pyskynet/skynet_py_foreign_seri.cpython-37m-x86_64-linux-gnu.so
pyskynet/proto.py
pyskynet/__init__.py
pyskynet/skynet_py_mq.cpython-37m-x86_64-linux-gnu.so
pyskynet/cluster.py
pyskynet/boot.py
pyskynet/foreign.py
pyskynet/skynet_py_main.cpython-37m-x86_64-linux-gnu.so
pyskynet/lualib/pyskynet.lua
pyskynet/lualib/rapidjson.so
pyskynet/lualib/protoc.lua
pyskynet/lualib/drlua.so
pyskynet/lualib/pb.so
pyskynet/lualib/numsky.so
pyskynet/lualib/pyskynet/cluster.lua
pyskynet/lualib/pyskynet/utils.lua
pyskynet/lualib/pyskynet/modify.so
pyskynet/lualib/pyskynet/foreign_seri.so
pyskynet/lualib/pyskynet/foreign.lua
pyskynet/service/pyholder.so
pyskynet/service/skynet_py_logger.lua
pyskynet/service/canvas_service.lua
pyskynet/service/fast_service.lua
pyskynet/service/foreign_clusterd.lua
pyskynet/service/foreign_clusteragent.lua
pyskynet/service/skynet_py_boot.lua
skynet/lualib/sproto.lua
skynet/lualib/skynet.lua
skynet/lualib/loader.lua
skynet/lualib/md5.lua
skynet/lualib/sprotoloader.lua
skynet/lualib/sprotoparser.lua
skynet/lualib/http/internal.lua
skynet/lualib/http/httpc.lua
skynet/lualib/http/httpd.lua
skynet/lualib/http/tlshelper.lua
skynet/lualib/http/sockethelper.lua
skynet/lualib/http/url.lua
skynet/lualib/http/websocket.lua
skynet/lualib/snax/hotfix.lua
skynet/lualib/snax/msgserver.lua
skynet/lualib/snax/gateserver.lua
skynet/lualib/snax/loginserver.lua
skynet/lualib/snax/interface.lua
skynet/lualib/compat10/memory.lua
skynet/lualib/compat10/multicast.lua
skynet/lualib/compat10/cluster.lua
skynet/lualib/compat10/sharedata.lua
skynet/lualib/compat10/redis.lua
skynet/lualib/compat10/datacenter.lua
skynet/lualib/compat10/profile.lua
skynet/lualib/compat10/crypt.lua
skynet/lualib/compat10/mongo.lua
skynet/lualib/compat10/stm.lua
skynet/lualib/compat10/socket.lua
skynet/lualib/compat10/socketdriver.lua
