Metadata-Version: 2.1
Name: pyskynet
Version: 0.0.3
Summary: PySkynet is a library for using skynet in python.
Home-page: UNKNOWN
Author: cz
Author-email: chenze.3057@bytedance.com
License: UNKNOWN
Platform: UNKNOWN
Requires-Python: >=3.6
License-File: LICENSE
Requires-Dist: cffi (~=1.14.2)
Requires-Dist: gevent (>=20.6.0)
